cheatlab/__init__.py
cheatlab/client.py
cheatlab-1.0.0.dist-info/licenses/LICENSE
cheatlab-1.0.0.dist-info/METADATA
cheatlab-1.0.0.dist-info/WHEEL
cheatlab-1.0.0.dist-info/top_level.txt
cheatlab-1.0.0.dist-info/RECORD
