Metadata-Version: 2.4
Name: cheatlab
Version: 1.0.0
Summary: Python client for CheatLab API - Quick command reference storage
Home-page: https://github.com/yourusername/cheatlab-python
Author: CheatLab
Author-email: 
License: MIT
Project-URL: Homepage, https://cheatlab.onrender.com
Project-URL: Documentation, https://github.com/yourusername/cheatlab-python
Project-URL: Repository, https://github.com/yourusername/cheatlab-python
Keywords: cheatlab,api,client,storage,reference
Classifier: Development Status :: 4 - Beta
Classifier: Intended Audience :: Developers
Classifier: Topic :: Software Development :: Libraries :: Python Modules
Classifier: License :: OSI Approved :: MIT License
Classifier: Programming Language :: Python :: 3
Classifier: Programming Language :: Python :: 3.7
Classifier: Programming Language :: Python :: 3.8
Classifier: Programming Language :: Python :: 3.9
Classifier: Programming Language :: Python :: 3.10
Classifier: Programming Language :: Python :: 3.11
Requires-Python: >=3.7
License-File: LICENSE
Requires-Dist: requests>=2.25.0
Dynamic: home-page
Dynamic: license-file
Dynamic: requires-python
